deworld/__init__.py
deworld/cartographer.py
deworld/configs/__init__.py
deworld/configs/base_config.py
deworld/exceptions.py
deworld/generate.py
deworld/layers/__init__.py
deworld/layers/atmosphere_layer.py
deworld/layers/base_layer.py
deworld/layers/height_layer.py
deworld/layers/soil_layer.py
deworld/layers/temperature_layer.py
deworld/layers/vegetation_layer.py
deworld/layers/wetness_layer.py
deworld/layers/wind_layer.py
deworld/map_colors.py
deworld/normalizers.py
deworld/power_points/__init__.py
deworld/power_points/arrow_area_point.py
deworld/power_points/base_point.py
deworld/power_points/circle_area_point.py
deworld/specifixation.txt
deworld/tests/__init__.py
deworld/tests/utils_tests.py
deworld/tests/vegetation_layer_tests.py
deworld/tests/wind_layer_tests.py
deworld/tests/world_tests.py
deworld/utils.py
deworld/world.py
deworld-0.2.3.dist-info/LICENSE
deworld-0.2.3.dist-info/WHEEL
deworld-0.2.3.dist-info/METADATA
deworld-0.2.3.dist-info/RECORD
