Metadata-Version: 2.1
Name: deworld
Version: 0.2.3
Summary: Developing world - python world generator.
Home-page: https://github.com/Tiendil/deworld
License: BSD-3
Keywords: gamedev,procedural content generation,map generation,terrain generation
Author: Aliaksei Yaletski (Tiendil)
Author-email: a.eletsky@gmail.com
Requires-Python: >=3.6,<4.0
Classifier: Development Status :: 5 - Production/Stable
Classifier: Intended Audience :: Developers
Classifier: License :: OSI Approved :: BSD License
Classifier: License :: Other/Proprietary License
Classifier: Programming Language :: Python :: 3
Classifier: Programming Language :: Python :: 3.10
Classifier: Programming Language :: Python :: 3.6
Classifier: Programming Language :: Python :: 3.7
Classifier: Programming Language :: Python :: 3.8
Classifier: Programming Language :: Python :: 3.9
Classifier: Topic :: Games/Entertainment
Classifier: Topic :: Software Development :: Libraries :: Python Modules
Project-URL: Repository, https://github.com/Tiendil/deworld
